glosario/.github/workflows/build.yml
glosario/.github/workflows/release.yml
glosario/__init__.py
glosario/data/glossary.yml
glosario/glosario.py
glosario-0.1.dist-info/LICENSE
glosario-0.1.dist-info/WHEEL
glosario-0.1.dist-info/METADATA
glosario-0.1.dist-info/RECORD
