Metadata-Version: 2.1
Name: glosario
Version: 0.1
Summary: Python package to define technical terms
License: MIT
Author: Ian Flores Siaca
Author-email: iflores.siaca@gmail.com
Requires-Python: >=3.7,<4.0
Classifier: License :: OSI Approved :: MIT License
Classifier: Programming Language :: Python :: 3
Classifier: Programming Language :: Python :: 3.7
Classifier: Programming Language :: Python :: 3.8
Requires-Dist: pyyaml (>=5.3.1,<6.0.0)
Requires-Dist: textdistance (>=4.2.0,<5.0.0)
